MANIFEST.in
README
setup.py
sphinxtheme_simple/__init__.py
sphinxtheme_simple/__init__.pyc
sphinxtheme_simple.egg-info/PKG-INFO
sphinxtheme_simple.egg-info/SOURCES.txt
sphinxtheme_simple.egg-info/dependency_links.txt
sphinxtheme_simple.egg-info/not-zip-safe
sphinxtheme_simple.egg-info/top_level.txt
sphinxtheme_simple/themes/simple/defindex.html
sphinxtheme_simple/themes/simple/domainindex.html
sphinxtheme_simple/themes/simple/genindex-single.html
sphinxtheme_simple/themes/simple/genindex-split.html
sphinxtheme_simple/themes/simple/genindex.html
sphinxtheme_simple/themes/simple/globaltoc.html
sphinxtheme_simple/themes/simple/layout.html
sphinxtheme_simple/themes/simple/localtoc.html
sphinxtheme_simple/themes/simple/opensearch.xml
sphinxtheme_simple/themes/simple/page.html
sphinxtheme_simple/themes/simple/relations.html
sphinxtheme_simple/themes/simple/search.html
sphinxtheme_simple/themes/simple/searchbox.html
sphinxtheme_simple/themes/simple/searchresults.html
sphinxtheme_simple/themes/simple/sourcelink.html
sphinxtheme_simple/themes/simple/theme.conf
sphinxtheme_simple/themes/simple/changes/frameset.html
sphinxtheme_simple/themes/simple/changes/rstsource.html
sphinxtheme_simple/themes/simple/changes/versionchanges.html
sphinxtheme_simple/themes/simple/static/ajax-loader.gif
sphinxtheme_simple/themes/simple/static/basic.css_t
sphinxtheme_simple/themes/simple/static/comment-bright.png
sphinxtheme_simple/themes/simple/static/comment-close.png
sphinxtheme_simple/themes/simple/static/comment.png
sphinxtheme_simple/themes/simple/static/doctools.js
sphinxtheme_simple/themes/simple/static/down-pressed.png
sphinxtheme_simple/themes/simple/static/down.png
sphinxtheme_simple/themes/simple/static/file.png
sphinxtheme_simple/themes/simple/static/jquery.js
sphinxtheme_simple/themes/simple/static/minus.png
sphinxtheme_simple/themes/simple/static/plus.png
sphinxtheme_simple/themes/simple/static/searchtools.js_t
sphinxtheme_simple/themes/simple/static/underscore.js
sphinxtheme_simple/themes/simple/static/up-pressed.png
sphinxtheme_simple/themes/simple/static/up.png
sphinxtheme_simple/themes/simple/static/websupport.js