Metadata-Version: 1.0
Name: sphinxtheme-simple
Version: 0.1
Summary: Simple sphinx theme
Home-page: http://pypi.python.org/pypi/sphinxtheme-simple
Author: Andrey Popp
Author-email: 8mayday@gmail.com
License: BSD3
Platform: UNKNOWN
